raddish/__init__.py
raddish/client.py
raddish/server.py
raddish/utils.py
raddish-0.2.4.dist-info/LICENSE.txt
raddish-0.2.4.dist-info/METADATA
raddish-0.2.4.dist-info/WHEEL
raddish-0.2.4.dist-info/RECORD
