Metadata-Version: 2.1
Name: raddish
Version: 0.2.4
Summary: Async-native Redis-backed RPC and job queue
License: Apache-2.0
Author: Daniil Larionov
Author-email: rexhaif.io@gmail.com
Requires-Python: >=3.10,<4.0
Classifier: License :: OSI Approved :: Apache Software License
Classifier: Programming Language :: Python :: 3
Classifier: Programming Language :: Python :: 3.10
Classifier: Programming Language :: Python :: 3.11
Requires-Dist: orjson (>=3.9.7,<4.0.0)
Requires-Dist: pydantic (>=2.2.0,<3.0.0)
Requires-Dist: redis (>=5.0.0,<6.0.0)
